DL_ANN/__init__.py
DL_ANN/perceptron.py
DL_ANN_pkg_VaibhavJoshi95-0.0.5.dist-info/LICENSE
DL_ANN_pkg_VaibhavJoshi95-0.0.5.dist-info/METADATA
DL_ANN_pkg_VaibhavJoshi95-0.0.5.dist-info/WHEEL
DL_ANN_pkg_VaibhavJoshi95-0.0.5.dist-info/top_level.txt
DL_ANN_pkg_VaibhavJoshi95-0.0.5.dist-info/RECORD
