Metadata-Version: 2.1
Name: DL-ANN-pkg-VaibhavJoshi95
Version: 0.0.5
Summary: A small package for perceptron
Home-page: https://github.com/VaibhavJoshi95/DL-ANN-pkg
Author: VaibhavJoshi95
Author-email: vaibhavgjoshi95@gmail.com
Project-URL: Bug Tracker, https://github.com/VaibhavJoshi95/DL-ANN-pkg/issues
Classifier: Programming Language :: Python :: 3
Classifier: License :: OSI Approved :: MIT License
Classifier: Operating System :: OS Independent
Requires-Python: >=3.9
License-File: LICENSE
Requires-Dist: numpy (==1.24.3)
Requires-Dist: pandas (==2.0.1)
Requires-Dist: joblib (==1.2.0)
Requires-Dist: matplotlib (==3.7.1)
